retriever_research/__init__.py
retriever_research/actor_watcher.py
retriever_research/config.py
retriever_research/log_viewer.py
retriever_research/logging.py
retriever_research/messages.py
retriever_research/retriever.py
retriever_research/shared_memory.py
retriever_research/ticker.py
retriever_research/actors/__init__.py
retriever_research/actors/chunk_sequencer.py
retriever_research/actors/file_chunker.py
retriever_research/actors/file_list_generator.py
retriever_research/actors/file_writer.py
retriever_research/actors/parallel_chunk_downloader.py
retriever_research/actors/pykka_extensions/__init__.py
retriever_research/actors/pykka_extensions/custom_actor.py
retriever_research/profiler/__init__.py
retriever_research/profiler/actors.py
retriever_research/profiler/collectors.py
retriever_research/profiler/event.py
retriever_research/profiler/profile.py
retriever_research/profiler/profiler.py
retriever_research/profiler/text_summary.py
retriever_research-0.0.5.dist-info/METADATA
retriever_research-0.0.5.dist-info/WHEEL
retriever_research-0.0.5.dist-info/entry_points.txt
retriever_research-0.0.5.dist-info/top_level.txt
retriever_research-0.0.5.dist-info/RECORD
