Metadata-Version: 2.1
Name: retriever-research
Version: 0.0.5
Summary: Fast, pure Python S3 downloader
Home-page: UNKNOWN
Author: Armand McQueen
Author-email: armandmcqueen@gmail.com
License: UNKNOWN
Platform: UNKNOWN
Classifier: Programming Language :: Python :: 3.7
Requires-Dist: pykka
Requires-Dist: boto3
Requires-Dist: tqdm
Requires-Dist: psutil
Requires-Dist: matplotlib
Requires-Dist: click
Requires-Dist: termcolor
